zjson/__init__.py
zjson/async_client.py
zjson/errors.py
zjson/object.py
zjson-1.3.0.dist-info/LICENSE
zjson-1.3.0.dist-info/METADATA
zjson-1.3.0.dist-info/WHEEL
zjson-1.3.0.dist-info/top_level.txt
zjson-1.3.0.dist-info/RECORD
