Metadata-Version: 2.1
Name: zjson
Version: 1.3.0
Summary: Json Database full async
Author: ZAID
Author-email: y8838@hotmail.com
Keywords: python,json,database,aio
Classifier: Development Status :: 1 - Planning
Classifier: Intended Audience :: Developers
Classifier: Programming Language :: Python :: 3
Classifier: Operating System :: Unix
Classifier: Operating System :: MacOS :: MacOS X
Classifier: Operating System :: Microsoft :: Windows
Requires-Python: ~=3.6
License-File: LICENSE
Requires-Dist: asyncio
Requires-Dist: aiofiles
